setup.cfg
setup.py
cmdline_csv2keychain.egg-info/PKG-INFO
cmdline_csv2keychain.egg-info/SOURCES.txt
cmdline_csv2keychain.egg-info/dependency_links.txt
cmdline_csv2keychain.egg-info/entry_points.txt
cmdline_csv2keychain.egg-info/top_level.txt
csv2keychain/__init__.py
csv2keychain/__main__.py
csv2keychain/csv2keychain-runner.py
csv2keychain/csv2keychain.py