Metadata-Version: 1.0
Name: cmdline-csv2keychain
Version: 0.1.3
Summary: Tool for adding exported credentials from Chrome to the macOS keychain.
Home-page: https://github.com/nntarasov/csv2keychain
Author: Nikita Tarasov
Author-email: mail@ntarasov.ru
License: UNKNOWN
Platform: UNKNOWN
